{
    "version": "2.2.0",
    "architecture": {
        "32bit": {
            "url": "https://github.com/meyermarcel/icm/releases/download/2.2.0/icm_Windows_i386.zip",
            "bin": [
                "icm.exe"
            ],
            "hash": "adb69ce246f7d3e0e3b425dd23a60761e3d3c16081848899e03dedb18106fc93"
        },
        "64bit": {
            "url": "https://github.com/meyermarcel/icm/releases/download/2.2.0/icm_Windows_x86_64.zip",
            "bin": [
                "icm.exe"
            ],
            "hash": "dd1f77b0667c8c5c30683ec06113b04bf37b59df4004efdc3019c9f48c873c2b"
        }
    },
    "homepage": "https://github.com/meyermarcel/icm",
    "license": "MIT",
    "description": "Generate or validate intermodal container markings."
}